smartapp/__init__.py
smartapp/converter.py
smartapp/dispatcher.py
smartapp/interface.py
smartapp/py.typed
smartapp/signature.py
smartapp_sdk-0.9.1.dist-info/METADATA
smartapp_sdk-0.9.1.dist-info/WHEEL
smartapp_sdk-0.9.1.dist-info/licenses/LICENSE
smartapp_sdk-0.9.1.dist-info/licenses/NOTICE
smartapp_sdk-0.9.1.dist-info/RECORD
