Metadata-Version: 2.4
Name: smartapp-sdk
Version: 0.9.1
Summary: Framework to build a webhook-based SmartThings SmartApp
Project-URL: Homepage, https://pypi.org/project/smartapp-sdk/
Project-URL: Repository, https://github.com/pronovic/smartapp-sdk
Project-URL: Changelog, https://github.com/pronovic/smartapp-sdk/releases
Project-URL: Documentation, https://smartapp-sdk.readthedocs.io/en/stable/
Project-URL: Issues, https://github.com/pronovic/smartapp-sdk/issues
Author-email: "Kenneth J. Pronovici" <pronovic@ieee.org>
License-Expression: Apache-2.0
License-File: LICENSE
License-File: NOTICE
Classifier: Development Status :: 4 - Beta
Classifier: Environment :: Console
Classifier: Intended Audience :: Developers
Classifier: Natural Language :: English
Classifier: Operating System :: OS Independent
Classifier: Programming Language :: Python :: 3
Classifier: Programming Language :: Python :: 3.11
Classifier: Programming Language :: Python :: 3.12
Classifier: Programming Language :: Python :: 3.13
Classifier: Programming Language :: Python :: 3.14
Classifier: Topic :: Home Automation
Classifier: Topic :: Software Development :: Libraries
Requires-Python: <4,>=3.11
Requires-Dist: arrow<2.0.0,>=1.3.0
Requires-Dist: attrs>=24.2.0
Requires-Dist: cattrs>=24.1.2
Requires-Dist: pycryptodomex<4.0.0,>=3.19.0
Requires-Dist: pyyaml<7.0.0,>=6.0.1
Requires-Dist: requests<3.0.0,>=2.31.0
Requires-Dist: tenacity<10.0.0,>=9.0.0
Provides-Extra: docs
Requires-Dist: sphinx-autoapi<4.0.0,>=3.3.3; extra == 'docs'
Requires-Dist: sphinx<9.0.0,>=8.1.3; extra == 'docs'
